comfydock_core/constants.py
comfydock_core/analyzers/custom_node_scanner.py
comfydock_core/analyzers/git_change_parser.py
comfydock_core/analyzers/model_scanner.py
comfydock_core/analyzers/node_classifier.py
comfydock_core/analyzers/node_git_analyzer.py
comfydock_core/analyzers/status_scanner.py
comfydock_core/analyzers/workflow_dependency_parser.py
comfydock_core/caching/__init__.py
comfydock_core/caching/api_cache.py
comfydock_core/caching/base.py
comfydock_core/caching/comfyui_cache.py
comfydock_core/caching/custom_node_cache.py
comfydock_core/caching/workflow_cache.py
comfydock_core/clients/__init__.py
comfydock_core/clients/civitai_client.py
comfydock_core/clients/github_client.py
comfydock_core/clients/registry_client.py
comfydock_core/configs/comfyui_builtin_nodes.py
comfydock_core/configs/comfyui_models.py
comfydock_core/configs/model_config.py
comfydock_core/core/environment.py
comfydock_core/core/workspace.py
comfydock_core/factories/environment_factory.py
comfydock_core/factories/uv_factory.py
comfydock_core/factories/workspace_factory.py
comfydock_core/infrastructure/sqlite_manager.py
comfydock_core/integrations/__init__.py
comfydock_core/integrations/uv_command.py
comfydock_core/logging/logging_config.py
comfydock_core/managers/export_import_manager.py
comfydock_core/managers/git_manager.py
comfydock_core/managers/model_download_manager.py
comfydock_core/managers/model_symlink_manager.py
comfydock_core/managers/node_manager.py
comfydock_core/managers/pyproject_manager.py
comfydock_core/managers/uv_project_manager.py
comfydock_core/managers/workflow_manager.py
comfydock_core/models/civitai.py
comfydock_core/models/commit.py
comfydock_core/models/environment.py
comfydock_core/models/exceptions.py
comfydock_core/models/manifest.py
comfydock_core/models/node_mapping.py
comfydock_core/models/protocols.py
comfydock_core/models/registry.py
comfydock_core/models/shared.py
comfydock_core/models/sync.py
comfydock_core/models/system.py
comfydock_core-1.0.11.dist-info/METADATA
comfydock_core-1.0.11.dist-info/WHEEL
comfydock_core-1.0.11.dist-info/licenses/LICENSE.txt
comfydock_core-1.0.11.dist-info/RECORD
